{"us-central1":[{"t":"a2-highgpu-1g","p":1.92802},{"t":"a2-highgpu-2g","p":3.85604},{"t":"a2-highgpu-4g","p":7.71208},{"t":"a2-highgpu-8g","p":15.42416},{"t":"a2-megagpu-16g","p":29.25568},{"t":"a2-ultragpu-1g","p":2.73756},{"t":"a2-ultragpu-2g","p":5.47512},{"t":"a2-ultragpu-4g","p":10.95024},{"t":"a2-ultragpu-8g","p":21.90048},{"t":"a3-edgegpu-8g","p":47.86592},{"t":"a3-edgegpu-8g-nolssd","p":47.86592},{"t":"a3-highgpu-1g","p":5.98324},{"t":"a3-highgpu-2g","p":11.96648},{"t":"a3-highgpu-4g","p":23.93296},{"t":"a3-highgpu-8g","p":47.86592},{"t":"a3-megagpu-8g","p":50.475072},{"t":"a3-ultragpu-8g","p":45.920744},{"t":"a3-ultragpu-8g-nolssd","p":45.920744},{"t":"c2-standard-16","p":0.362528},{"t":"c2-standard-30","p":0.67974},{"t":"c2-standard-4","p":0.090632},{"t":"c2-standard-60","p":1.35948},{"t":"c2-standard-8","p":0.181264},{"t":"c2d-highcpu-112","p":1.281056},{"t":"c2d-highcpu-16","p":0.183008},{"t":"c2d-highcpu-2","p":0.022876},{"t":"c2d-highcpu-32","p":0.366016},{"t":"c2d-highcpu-4","p":0.045752},{"t":"c2d-highcpu-56","p":0.640528},{"t":"c2d-highcpu-8","p":0.091504},{"t":"c2d-highmem-112","p":2.0935040000000003},{"t":"c2d-highmem-16","p":0.299072},{"t":"c2d-highmem-2","p":0.037384},{"t":"c2d-highmem-32","p":0.598144},{"t":"c2d-highmem-4","p":0.074768},{"t":"c2d-highmem-56","p":1.0467520000000001},{"t":"c2d-highmem-8","p":0.149536},{"t":"c2d-standard-112","p":1.551872},{"t":"c2d-standard-16","p":0.221696},{"t":"c2d-standard-2","p":0.027712},{"t":"c2d-standard-32","p":0.443392},{"t":"c2d-standard-4","p":0.055424},{"t":"c2d-standard-56","p":0.775936},{"t":"c2d-standard-8","p":0.110848},{"t":"c3-highcpu-176","p":1.745568},{"t":"c3-highcpu-192-metal","p":2.021888},{"t":"c3-highcpu-22","p":0.218196},{"t":"c3-highcpu-4","p":0.039672},{"t":"c3-highcpu-44","p":0.436392},{"t":"c3-highcpu-8","p":0.079344},{"t":"c3-highcpu-88","p":0.872784},{"t":"c3-highmem-176","p":2.7160320000000002},{"t":"c3-highmem-192-metal","p":2.9629440000000002},{"t":"c3-highmem-22","p":0.33950400000000003},{"t":"c3-highmem-4","p":0.061728000000000005},{"t":"c3-highmem-44","p":0.6790080000000001},{"t":"c3-highmem-8","p":0.12345600000000001},{"t":"c3-highmem-88","p":1.3580160000000001},{"t":"c3-standard-176","p":2.069056},{"t":"c3-standard-176-lssd","p":2.069056},{"t":"c3-standard-192-metal","p":2.257152},{"t":"c3-standard-22","p":0.258632},{"t":"c3-standard-22-lssd","p":0.258632},{"t":"c3-standard-4","p":0.047024},{"t":"c3-standard-4-lssd","p":0.047024},{"t":"c3-standard-44","p":0.517264},{"t":"c3-standard-44-lssd","p":0.517264},{"t":"c3-standard-8","p":0.094048},{"t":"c3-standard-8-lssd","p":0.094048},{"t":"c3-standard-88","p":1.034528},{"t":"c3-standard-88-lssd","p":1.034528},{"t":"c3d-highcpu-16","p":0.1272},{"t":"c3d-highcpu-180","p":1.4259600000000001},{"t":"c3d-highcpu-30","p":0.23766},{"t":"c3d-highcpu-360","p":2.8519200000000002},{"t":"c3d-highcpu-4","p":0.0318},{"t":"c3d-highcpu-60","p":0.47532},{"t":"c3d-highcpu-8","p":0.0636},{"t":"c3d-highcpu-90","p":0.7129800000000001},{"t":"c3d-highmem-16","p":0.20784000000000002},{"t":"c3d-highmem-16-lssd","p":0.20784000000000002},{"t":"c3d-highmem-180","p":2.3382},{"t":"c3d-highmem-180-lssd","p":2.3382},{"t":"c3d-highmem-30","p":0.38970000000000005},{"t":"c3d-highmem-30-lssd","p":0.38970000000000005},{"t":"c3d-highmem-360","p":4.6764},{"t":"c3d-highmem-360-lssd","p":4.6764},{"t":"c3d-highmem-4","p":0.051960000000000006},{"t":"c3d-highmem-60","p":0.7794000000000001},{"t":"c3d-highmem-60-lssd","p":0.7794000000000001},{"t":"c3d-highmem-8","p":0.10392000000000001},{"t":"c3d-highmem-8-lssd","p":0.10392000000000001},{"t":"c3d-highmem-90","p":1.1691},{"t":"c3d-highmem-90-lssd","p":1.1691},{"t":"c3d-standard-16","p":0.15408},{"t":"c3d-standard-16-lssd","p":0.15408},{"t":"c3d-standard-180","p":1.7334},{"t":"c3d-standard-180-lssd","p":1.7334},{"t":"c3d-standard-30","p":0.28890000000000005},{"t":"c3d-standard-30-lssd","p":0.28890000000000005},{"t":"c3d-standard-360","p":3.4668},{"t":"c3d-standard-360-lssd","p":3.4668},{"t":"c3d-standard-4","p":0.03852},{"t":"c3d-standard-60","p":0.5778000000000001},{"t":"c3d-standard-60-lssd","p":0.5778000000000001},{"t":"c3d-standard-8","p":0.07704},{"t":"c3d-standard-8-lssd","p":0.07704},{"t":"c3d-standard-90","p":0.8667},{"t":"c3d-standard-90-lssd","p":0.8667},{"t":"c4-highcpu-144","p":3.534624},{"t":"c4-highcpu-16","p":0.39273600000000003},{"t":"c4-highcpu-192","p":4.712832},{"t":"c4-highcpu-2","p":0.049092000000000004},{"t":"c4-highcpu-24","p":0.589104},{"t":"c4-highcpu-288","p":7.069248},{"t":"c4-highcpu-288-metal","p":4.898304},{"t":"c4-highcpu-32","p":0.7854720000000001},{"t":"c4-highcpu-4","p":0.09818400000000001},{"t":"c4-highcpu-48","p":1.178208},{"t":"c4-highcpu-8","p":0.19636800000000001},{"t":"c4-highcpu-96","p":2.356416},{"t":"c4-highmem-144","p":5.416668},{"t":"c4-highmem-144-lssd","p":5.416668},{"t":"c4-highmem-16","p":0.601852},{"t":"c4-highmem-16-lssd","p":0.601852},{"t":"c4-highmem-192","p":7.222224000000001},{"t":"c4-highmem-192-lssd","p":7.222224000000001},{"t":"c4-highmem-2","p":0.07409500000000001},{"t":"c4-highmem-24","p":0.9027780000000001},{"t":"c4-highmem-24-lssd","p":0.9027780000000001},{"t":"c4-highmem-288","p":10.833336},{"t":"c4-highmem-288-lssd","p":10.833336},{"t":"c4-highmem-288-lssd-metal","p":10.833336},{"t":"c4-highmem-288-metal","p":10.833336},{"t":"c4-highmem-32","p":1.203704},{"t":"c4-highmem-32-lssd","p":1.203704},{"t":"c4-highmem-4","p":0.150463},{"t":"c4-highmem-4-lssd","p":0.150463},{"t":"c4-highmem-48","p":1.8055560000000002},{"t":"c4-highmem-48-lssd","p":1.8055560000000002},{"t":"c4-highmem-8","p":0.300926},{"t":"c4-highmem-8-lssd","p":0.300926},{"t":"c4-highmem-96","p":3.6111120000000003},{"t":"c4-highmem-96-lssd","p":3.6111120000000003},{"t":"c4-standard-144","p":4.10742},{"t":"c4-standard-144-lssd","p":4.10742},{"t":"c4-standard-16","p":0.45638},{"t":"c4-standard-16-lssd","p":0.45638},{"t":"c4-standard-192","p":5.47656},{"t":"c4-standard-192-lssd","p":5.47656},{"t":"c4-standard-2","p":0.055911},{"t":"c4-standard-24","p":0.68457},{"t":"c4-standard-24-lssd","p":0.68457},{"t":"c4-standard-288","p":8.21484},{"t":"c4-standard-288-lssd","p":8.21484},{"t":"c4-standard-288-lssd-metal","p":8.21484},{"t":"c4-standard-288-metal","p":8.21484},{"t":"c4-standard-32","p":0.91276},{"t":"c4-standard-32-lssd","p":0.91276},{"t":"c4-standard-4","p":0.114095},{"t":"c4-standard-4-lssd","p":0.114095},{"t":"c4-standard-48","p":1.36914},{"t":"c4-standard-48-lssd","p":1.36914},{"t":"c4-standard-8","p":0.22819},{"t":"c4-standard-8-lssd","p":0.22819},{"t":"c4-standard-96","p":2.73828},{"t":"c4-standard-96-lssd","p":2.73828},{"t":"c4a-highcpu-1","p":0.015590000000000001},{"t":"c4a-highcpu-16","p":0.24944000000000002},{"t":"c4a-highcpu-2","p":0.031180000000000003},{"t":"c4a-highcpu-32","p":0.49888000000000005},{"t":"c4a-highcpu-4","p":0.062360000000000006},{"t":"c4a-highcpu-48","p":0.7483200000000001},{"t":"c4a-highcpu-64","p":0.9977600000000001},{"t":"c4a-highcpu-72","p":1.1224800000000001},{"t":"c4a-highcpu-8","p":0.12472000000000001},{"t":"c4a-highmem-1","p":0.024260000000000004},{"t":"c4a-highmem-16","p":0.38816000000000006},{"t":"c4a-highmem-16-lssd","p":0.38816000000000006},{"t":"c4a-highmem-2","p":0.04852000000000001},{"t":"c4a-highmem-32","p":0.7763200000000001},{"t":"c4a-highmem-32-lssd","p":0.7763200000000001},{"t":"c4a-highmem-4","p":0.09704000000000002},{"t":"c4a-highmem-4-lssd","p":0.09704000000000002},{"t":"c4a-highmem-48","p":1.1644800000000002},{"t":"c4a-highmem-48-lssd","p":1.1644800000000002},{"t":"c4a-highmem-64","p":1.5526400000000002},{"t":"c4a-highmem-64-lssd","p":1.5526400000000002},{"t":"c4a-highmem-72","p":1.7467200000000003},{"t":"c4a-highmem-72-lssd","p":1.7467200000000003},{"t":"c4a-highmem-8","p":0.19408000000000003},{"t":"c4a-highmem-8-lssd","p":0.19408000000000003},{"t":"c4a-highmem-96-metal","p":2.3289600000000004},{"t":"c4a-standard-1","p":0.018480000000000003},{"t":"c4a-standard-16","p":0.29568000000000005},{"t":"c4a-standard-16-lssd","p":0.29568000000000005},{"t":"c4a-standard-2","p":0.03696000000000001},{"t":"c4a-standard-32","p":0.5913600000000001},{"t":"c4a-standard-32-lssd","p":0.5913600000000001},{"t":"c4a-standard-4","p":0.07392000000000001},{"t":"c4a-standard-4-lssd","p":0.07392000000000001},{"t":"c4a-standard-48","p":0.88704},{"t":"c4a-standard-48-lssd","p":0.88704},{"t":"c4a-standard-64","p":1.1827200000000002},{"t":"c4a-standard-64-lssd","p":1.1827200000000002},{"t":"c4a-standard-72","p":1.3305600000000002},{"t":"c4a-standard-72-lssd","p":1.3305600000000002},{"t":"c4a-standard-8","p":0.14784000000000003},{"t":"c4a-standard-8-lssd","p":0.14784000000000003},{"t":"c4d-highcpu-16","p":0.22049000000000002},{"t":"c4d-highcpu-192","p":2.64588},{"t":"c4d-highcpu-2","p":0.026641},{"t":"c4d-highcpu-32","p":0.44098000000000004},{"t":"c4d-highcpu-384","p":5.29176},{"t":"c4d-highcpu-4","p":0.054509},{"t":"c4d-highcpu-48","p":0.66147},{"t":"c4d-highcpu-64","p":0.8819600000000001},{"t":"c4d-highcpu-8","p":0.11024500000000001},{"t":"c4d-highcpu-96","p":1.32294},{"t":"c4d-highmem-16","p":0.33828199999999997},{"t":"c4d-highmem-16-lssd","p":0.33828199999999997},{"t":"c4d-highmem-192","p":4.059384},{"t":"c4d-highmem-192-lssd","p":4.059384},{"t":"c4d-highmem-2","p":0.041365},{"t":"c4d-highmem-32","p":0.6765639999999999},{"t":"c4d-highmem-32-lssd","p":0.6765639999999999},{"t":"c4d-highmem-384","p":8.118768},{"t":"c4d-highmem-384-lssd","p":8.118768},{"t":"c4d-highmem-4","p":0.083957},{"t":"c4d-highmem-48","p":1.014846},{"t":"c4d-highmem-48-lssd","p":1.014846},{"t":"c4d-highmem-64","p":1.3531279999999999},{"t":"c4d-highmem-64-lssd","p":1.3531279999999999},{"t":"c4d-highmem-8","p":0.16914099999999999},{"t":"c4d-highmem-8-lssd","p":0.16914099999999999},{"t":"c4d-highmem-96","p":2.029692},{"t":"c4d-highmem-96-lssd","p":2.029692},{"t":"c4d-standard-16","p":0.25975400000000004},{"t":"c4d-standard-16-lssd","p":0.25975400000000004},{"t":"c4d-standard-192","p":3.117048},{"t":"c4d-standard-192-lssd","p":3.117048},{"t":"c4d-standard-2","p":0.031549},{"t":"c4d-standard-32","p":0.5195080000000001},{"t":"c4d-standard-32-lssd","p":0.5195080000000001},{"t":"c4d-standard-384","p":6.234096},{"t":"c4d-standard-384-lssd","p":6.234096},{"t":"c4d-standard-384-metal","p":6.292992},{"t":"c4d-standard-4","p":0.06432500000000001},{"t":"c4d-standard-48","p":0.779262},{"t":"c4d-standard-48-lssd","p":0.779262},{"t":"c4d-standard-64","p":1.0390160000000002},{"t":"c4d-standard-64-lssd","p":1.0390160000000002},{"t":"c4d-standard-8","p":0.12987700000000002},{"t":"c4d-standard-8-lssd","p":0.12987700000000002},{"t":"c4d-standard-96","p":1.558524},{"t":"c4d-standard-96-lssd","p":1.558524},{"t":"c4n-highcpu-16","p":0.435469},{"t":"c4n-highcpu-192","p":5.225626},{"t":"c4n-highcpu-2","p":0.054434},{"t":"c4n-highcpu-24","p":0.653203},{"t":"c4n-highcpu-4","p":0.108867},{"t":"c4n-highcpu-48","p":1.306406},{"t":"c4n-highcpu-8","p":0.217734},{"t":"c4n-highcpu-96","p":2.612813},{"t":"c4n-highmem-16","p":0.667346},{"t":"c4n-highmem-192","p":8.008147},{"t":"c4n-highmem-2","p":0.082158},{"t":"c4n-highmem-24","p":1.001018},{"t":"c4n-highmem-4","p":0.166836},{"t":"c4n-highmem-48","p":2.002037},{"t":"c4n-highmem-8","p":0.333673},{"t":"c4n-highmem-96","p":4.004074},{"t":"c4n-standard-16","p":0.50604},{"t":"c4n-standard-192","p":6.07248},{"t":"c4n-standard-2","p":0.061995},{"t":"c4n-standard-24","p":0.75906},{"t":"c4n-standard-4","p":0.12651},{"t":"c4n-standard-48","p":1.51812},{"t":"c4n-standard-8","p":0.25302},{"t":"c4n-standard-96","p":3.03624},{"t":"e2-highcpu-16","p":0.22843200000000002},{"t":"e2-highcpu-2","p":0.028554000000000003},{"t":"e2-highcpu-32","p":0.45686400000000005},{"t":"e2-highcpu-4","p":0.057108000000000006},{"t":"e2-highcpu-8","p":0.11421600000000001},{"t":"e2-highmem-16","p":0.417376},{"t":"e2-highmem-2","p":0.052172},{"t":"e2-highmem-4","p":0.104344},{"t":"e2-highmem-8","p":0.208688},{"t":"e2-medium","p":0.031928},{"t":"e2-micro","p":0.026867000000000002},{"t":"e2-small","p":0.028554000000000003},{"t":"e2-standard-16","p":0.309408},{"t":"e2-standard-2","p":0.038676},{"t":"e2-standard-32","p":0.618816},{"t":"e2-standard-4","p":0.077352},{"t":"e2-standard-8","p":0.154704},{"t":"f1-micro","p":0.000684},{"t":"g1-small","p":0.002313},{"t":"g2-standard-12","p":0.511248},{"t":"g2-standard-16","p":0.586264},{"t":"g2-standard-24","p":1.022496},{"t":"g2-standard-32","p":0.886328},{"t":"g2-standard-4","p":0.361216},{"t":"g2-standard-48","p":2.044992},{"t":"g2-standard-8","p":0.436232},{"t":"g2-standard-96","p":4.089984},{"t":"h3-standard-88","p":2.82744},{"t":"h4d-highmem-192","p":3.713808},{"t":"h4d-highmem-192-lssd","p":3.713808},{"t":"h4d-standard-192","p":3.29832},{"t":"m1-megamem-96","p":1.9629436328125003},{"t":"m1-ultramem-160","p":4.63896},{"t":"m1-ultramem-40","p":1.15974},{"t":"m1-ultramem-80","p":2.31948},{"t":"m3-megamem-128","p":7.945344},{"t":"m3-megamem-64","p":3.972672},{"t":"m3-ultramem-128","p":13.434368000000001},{"t":"m3-ultramem-32","p":3.3585920000000002},{"t":"m3-ultramem-64","p":6.7171840000000005},{"t":"m4-hypermem-16","p":0.784272},{"t":"m4-hypermem-32","p":1.568544},{"t":"m4-hypermem-64","p":3.137088},{"t":"m4-megamem-112","p":4.866432},{"t":"m4-megamem-224","p":9.732864},{"t":"m4-megamem-28","p":1.216608},{"t":"m4-megamem-56","p":2.433216},{"t":"m4-ultramem-112","p":8.607264},{"t":"m4-ultramem-224","p":17.214528},{"t":"m4-ultramem-56","p":4.303632},{"t":"n1-highcpu-16","p":0.190411755859375},{"t":"n1-highcpu-2","p":0.023801122070312503},{"t":"n1-highcpu-32","p":0.3808221220703125},{"t":"n1-highcpu-4","p":0.04760224414062501},{"t":"n1-highcpu-64","p":0.761644244140625},{"t":"n1-highcpu-8","p":0.0952058779296875},{"t":"n1-highcpu-96","p":1.142467755859375},{"t":"n1-highmem-16","p":0.31791200000000003},{"t":"n1-highmem-2","p":0.039739000000000003},{"t":"n1-highmem-32","p":0.6358240000000001},{"t":"n1-highmem-4","p":0.07947800000000001},{"t":"n1-highmem-64","p":1.2716480000000001},{"t":"n1-highmem-8","p":0.15895600000000001},{"t":"n1-highmem-96","p":1.9074719999999998},{"t":"n1-megamem-96","p":3.059532244140625},{"t":"n1-standard-1","p":0.01595625},{"t":"n1-standard-16","p":0.2553},{"t":"n1-standard-2","p":0.0319125},{"t":"n1-standard-32","p":0.5106},{"t":"n1-standard-4","p":0.063825},{"t":"n1-standard-64","p":1.0212},{"t":"n1-standard-8","p":0.12765},{"t":"n1-standard-96","p":1.5318},{"t":"n1-ultramem-160","p":7.169212},{"t":"n1-ultramem-40","p":1.792303},{"t":"n1-ultramem-80","p":3.584606},{"t":"n2-highcpu-16","p":0.24731200000000003},{"t":"n2-highcpu-2","p":0.030914000000000004},{"t":"n2-highcpu-32","p":0.49462400000000006},{"t":"n2-highcpu-4","p":0.06182800000000001},{"t":"n2-highcpu-48","p":0.741936},{"t":"n2-highcpu-64","p":0.9892480000000001},{"t":"n2-highcpu-8","p":0.12365600000000002},{"t":"n2-highcpu-80","p":1.23656},{"t":"n2-highcpu-96","p":1.483872},{"t":"n2-highmem-128","p":3.3231680000000003},{"t":"n2-highmem-16","p":0.451936},{"t":"n2-highmem-2","p":0.056492},{"t":"n2-highmem-32","p":0.903872},{"t":"n2-highmem-4","p":0.112984},{"t":"n2-highmem-48","p":1.3558080000000001},{"t":"n2-highmem-64","p":1.807744},{"t":"n2-highmem-8","p":0.225968},{"t":"n2-highmem-80","p":2.2596800000000004},{"t":"n2-highmem-96","p":2.7116160000000002},{"t":"n2-standard-128","p":2.6800640000000002},{"t":"n2-standard-16","p":0.33500800000000003},{"t":"n2-standard-2","p":0.041876000000000003},{"t":"n2-standard-32","p":0.6700160000000001},{"t":"n2-standard-4","p":0.08375200000000001},{"t":"n2-standard-48","p":1.0050240000000001},{"t":"n2-standard-64","p":1.3400320000000001},{"t":"n2-standard-8","p":0.16750400000000001},{"t":"n2-standard-80","p":1.67504},{"t":"n2-standard-96","p":2.0100480000000003},{"t":"n2d-highcpu-128","p":1.05088},{"t":"n2d-highcpu-16","p":0.13136},{"t":"n2d-highcpu-2","p":0.01642},{"t":"n2d-highcpu-224","p":1.83904},{"t":"n2d-highcpu-32","p":0.26272},{"t":"n2d-highcpu-4","p":0.03284},{"t":"n2d-highcpu-48","p":0.39408000000000004},{"t":"n2d-highcpu-64","p":0.52544},{"t":"n2d-highcpu-8","p":0.06568},{"t":"n2d-highcpu-80","p":0.6568},{"t":"n2d-highcpu-96","p":0.7881600000000001},{"t":"n2d-highmem-16","p":0.24000000000000002},{"t":"n2d-highmem-2","p":0.030000000000000002},{"t":"n2d-highmem-32","p":0.48000000000000004},{"t":"n2d-highmem-4","p":0.060000000000000005},{"t":"n2d-highmem-48","p":0.7200000000000001},{"t":"n2d-highmem-64","p":0.9600000000000001},{"t":"n2d-highmem-8","p":0.12000000000000001},{"t":"n2d-highmem-80","p":1.2000000000000002},{"t":"n2d-highmem-96","p":1.4400000000000002},{"t":"n2d-standard-128","p":1.4233600000000002},{"t":"n2d-standard-16","p":0.17792000000000002},{"t":"n2d-standard-2","p":0.022240000000000003},{"t":"n2d-standard-224","p":2.49088},{"t":"n2d-standard-32","p":0.35584000000000005},{"t":"n2d-standard-4","p":0.044480000000000006},{"t":"n2d-standard-48","p":0.53376},{"t":"n2d-standard-64","p":0.7116800000000001},{"t":"n2d-standard-8","p":0.08896000000000001},{"t":"n2d-standard-80","p":0.8896000000000001},{"t":"n2d-standard-96","p":1.06752},{"t":"n4-highcpu-16","p":0.28800000000000003},{"t":"n4-highcpu-2","p":0.036000000000000004},{"t":"n4-highcpu-32","p":0.5760000000000001},{"t":"n4-highcpu-4","p":0.07200000000000001},{"t":"n4-highcpu-48","p":0.864},{"t":"n4-highcpu-64","p":1.1520000000000001},{"t":"n4-highcpu-8","p":0.14400000000000002},{"t":"n4-highcpu-80","p":1.44},{"t":"n4-highmem-16","p":0.44784},{"t":"n4-highmem-2","p":0.05598},{"t":"n4-highmem-32","p":0.89568},{"t":"n4-highmem-4","p":0.11196},{"t":"n4-highmem-48","p":1.34352},{"t":"n4-highmem-64","p":1.79136},{"t":"n4-highmem-8","p":0.22392},{"t":"n4-highmem-80","p":2.2392000000000003},{"t":"n4-standard-16","p":0.34128000000000003},{"t":"n4-standard-2","p":0.042660000000000003},{"t":"n4-standard-32","p":0.6825600000000001},{"t":"n4-standard-4","p":0.08532000000000001},{"t":"n4-standard-48","p":1.02384},{"t":"n4-standard-64","p":1.3651200000000001},{"t":"n4-standard-8","p":0.17064000000000001},{"t":"n4-standard-80","p":1.7064},{"t":"n4a-highcpu-1","p":0.013638},{"t":"n4a-highcpu-16","p":0.218208},{"t":"n4a-highcpu-2","p":0.027276},{"t":"n4a-highcpu-32","p":0.436416},{"t":"n4a-highcpu-4","p":0.054552},{"t":"n4a-highcpu-48","p":0.654624},{"t":"n4a-highcpu-64","p":0.872832},{"t":"n4a-highcpu-8","p":0.109104},{"t":"n4a-highmem-1","p":0.021222},{"t":"n4a-highmem-16","p":0.339552},{"t":"n4a-highmem-2","p":0.042444},{"t":"n4a-highmem-32","p":0.679104},{"t":"n4a-highmem-4","p":0.084888},{"t":"n4a-highmem-48","p":1.018656},{"t":"n4a-highmem-64","p":1.358208},{"t":"n4a-highmem-8","p":0.169776},{"t":"n4a-standard-1","p":0.016166},{"t":"n4a-standard-16","p":0.258656},{"t":"n4a-standard-2","p":0.032332},{"t":"n4a-standard-32","p":0.517312},{"t":"n4a-standard-4","p":0.064664},{"t":"n4a-standard-48","p":0.775968},{"t":"n4a-standard-64","p":1.034624},{"t":"n4a-standard-8","p":0.129328},{"t":"n4d-highcpu-16","p":0.277312},{"t":"n4d-highcpu-2","p":0.034664},{"t":"n4d-highcpu-32","p":0.554624},{"t":"n4d-highcpu-4","p":0.069328},{"t":"n4d-highcpu-48","p":0.831936},{"t":"n4d-highcpu-64","p":1.109248},{"t":"n4d-highcpu-8","p":0.138656},{"t":"n4d-highcpu-80","p":1.38656},{"t":"n4d-highcpu-96","p":1.663872},{"t":"n4d-highmem-16","p":0.431488},{"t":"n4d-highmem-2","p":0.053936},{"t":"n4d-highmem-32","p":0.862976},{"t":"n4d-highmem-4","p":0.107872},{"t":"n4d-highmem-48","p":1.294464},{"t":"n4d-highmem-64","p":1.725952},{"t":"n4d-highmem-8","p":0.215744},{"t":"n4d-highmem-80","p":2.1574400000000002},{"t":"n4d-highmem-96","p":2.588928},{"t":"n4d-standard-16","p":0.328704},{"t":"n4d-standard-2","p":0.041088},{"t":"n4d-standard-32","p":0.657408},{"t":"n4d-standard-4","p":0.082176},{"t":"n4d-standard-48","p":0.9861120000000001},{"t":"n4d-standard-64","p":1.314816},{"t":"n4d-standard-8","p":0.164352},{"t":"n4d-standard-80","p":1.64352},{"t":"n4d-standard-96","p":1.9722240000000002},{"t":"t2a-standard-1","p":0.014904},{"t":"t2a-standard-16","p":0.238464},{"t":"t2a-standard-2","p":0.029808},{"t":"t2a-standard-32","p":0.476928},{"t":"t2a-standard-4","p":0.059616},{"t":"t2a-standard-48","p":0.715392},{"t":"t2a-standard-8","p":0.119232},{"t":"t2d-standard-1","p":0.01432},{"t":"t2d-standard-16","p":0.22912},{"t":"t2d-standard-2","p":0.02864},{"t":"t2d-standard-32","p":0.45824},{"t":"t2d-standard-4","p":0.05728},{"t":"t2d-standard-48","p":0.68736},{"t":"t2d-standard-60","p":0.8592},{"t":"t2d-standard-8","p":0.11456},{"t":"z3-highmem-14-standardlssd","p":0.5345200000000001},{"t":"z3-highmem-16-highlssd","p":0.6108800000000001},{"t":"z3-highmem-176","p":6.71968},{"t":"z3-highmem-176-standardlssd","p":6.71968},{"t":"z3-highmem-192-highlssd-metal","p":7.33056},{"t":"z3-highmem-22-highlssd","p":0.83996},{"t":"z3-highmem-22-standardlssd","p":0.83996},{"t":"z3-highmem-32-highlssd","p":1.2217600000000002},{"t":"z3-highmem-44-highlssd","p":1.67992},{"t":"z3-highmem-44-standardlssd","p":1.67992},{"t":"z3-highmem-8-highlssd","p":0.30544000000000004},{"t":"z3-highmem-88","p":3.35984},{"t":"z3-highmem-88-highlssd","p":3.35984},{"t":"z3-highmem-88-standardlssd","p":3.35984}],"us-east4":[{"t":"a2-ultragpu-1g","p":2.30622},{"t":"a2-ultragpu-2g","p":4.61244},{"t":"a2-ultragpu-4g","p":9.22488},{"t":"a2-ultragpu-8g","p":18.44976},{"t":"a3-edgegpu-8g","p":34.159968},{"t":"a3-edgegpu-8g-nolssd","p":34.159968},{"t":"a3-highgpu-1g","p":4.269996},{"t":"a3-highgpu-2g","p":8.539992},{"t":"a3-highgpu-4g","p":17.079984},{"t":"a3-highgpu-8g","p":34.159968},{"t":"a3-megagpu-8g","p":20.233824000000002},{"t":"a3-ultragpu-8g","p":40.024944000000005},{"t":"a3-ultragpu-8g-nolssd","p":40.024944000000005},{"t":"c2-standard-16","p":0.339648},{"t":"c2-standard-30","p":0.6368400000000001},{"t":"c2-standard-4","p":0.084912},{"t":"c2-standard-60","p":1.2736800000000001},{"t":"c2-standard-8","p":0.169824},{"t":"c2d-highcpu-112","p":1.1912319999999998},{"t":"c2d-highcpu-16","p":0.170176},{"t":"c2d-highcpu-2","p":0.021272},{"t":"c2d-highcpu-32","p":0.340352},{"t":"c2d-highcpu-4","p":0.042544},{"t":"c2d-highcpu-56","p":0.5956159999999999},{"t":"c2d-highcpu-8","p":0.085088},{"t":"c2d-highmem-112","p":1.945888},{"t":"c2d-highmem-16","p":0.277984},{"t":"c2d-highmem-2","p":0.034748},{"t":"c2d-highmem-32","p":0.555968},{"t":"c2d-highmem-4","p":0.069496},{"t":"c2d-highmem-56","p":0.972944},{"t":"c2d-highmem-8","p":0.138992},{"t":"c2d-standard-112","p":1.442784},{"t":"c2d-standard-16","p":0.20611200000000002},{"t":"c2d-standard-2","p":0.025764000000000002},{"t":"c2d-standard-32","p":0.41222400000000003},{"t":"c2d-standard-4","p":0.051528000000000004},{"t":"c2d-standard-56","p":0.721392},{"t":"c2d-standard-8","p":0.10305600000000001},{"t":"c3-highcpu-176","p":2.237664},{"t":"c3-highcpu-192-metal","p":2.5917440000000003},{"t":"c3-highcpu-22","p":0.279708},{"t":"c3-highcpu-4","p":0.050856000000000005},{"t":"c3-highcpu-44","p":0.559416},{"t":"c3-highcpu-8","p":0.10171200000000001},{"t":"c3-highcpu-88","p":1.118832},{"t":"c3-highmem-176","p":3.480576},{"t":"c3-highmem-192-metal","p":3.7969920000000004},{"t":"c3-highmem-22","p":0.435072},{"t":"c3-highmem-4","p":0.07910400000000001},{"t":"c3-highmem-44","p":0.870144},{"t":"c3-highmem-8","p":0.15820800000000002},{"t":"c3-highmem-88","p":1.740288},{"t":"c3-standard-176","p":2.651968},{"t":"c3-standard-176-lssd","p":2.651968},{"t":"c3-standard-192-metal","p":2.8930560000000005},{"t":"c3-standard-22","p":0.331496},{"t":"c3-standard-22-lssd","p":0.331496},{"t":"c3-standard-4","p":0.060272000000000006},{"t":"c3-standard-4-lssd","p":0.060272000000000006},{"t":"c3-standard-44","p":0.662992},{"t":"c3-standard-44-lssd","p":0.662992},{"t":"c3-standard-8","p":0.12054400000000001},{"t":"c3-standard-8-lssd","p":0.12054400000000001},{"t":"c3-standard-88","p":1.325984},{"t":"c3-standard-88-lssd","p":1.325984},{"t":"c3d-highcpu-16","p":0.260672},{"t":"c3d-highcpu-180","p":2.9222340000000004},{"t":"c3d-highcpu-30","p":0.487039},{"t":"c3d-highcpu-360","p":5.844468000000001},{"t":"c3d-highcpu-4","p":0.065168},{"t":"c3d-highcpu-60","p":0.974078},{"t":"c3d-highcpu-8","p":0.130336},{"t":"c3d-highcpu-90","p":1.4611170000000002},{"t":"c3d-highmem-16","p":0.42588800000000004},{"t":"c3d-highmem-16-lssd","p":0.3919},{"t":"c3d-highmem-180","p":4.79124},{"t":"c3d-highmem-180-lssd","p":4.4089},{"t":"c3d-highmem-30","p":0.79854},{"t":"c3d-highmem-30-lssd","p":0.7348},{"t":"c3d-highmem-360","p":9.58248},{"t":"c3d-highmem-360-lssd","p":8.8178},{"t":"c3d-highmem-4","p":0.10647200000000001},{"t":"c3d-highmem-60","p":1.59708},{"t":"c3d-highmem-60-lssd","p":1.4696},{"t":"c3d-highmem-8","p":0.21294400000000002},{"t":"c3d-highmem-8-lssd","p":0.196},{"t":"c3d-highmem-90","p":2.39562},{"t":"c3d-highmem-90-lssd","p":2.2045},{"t":"c3d-standard-16","p":0.315744},{"t":"c3d-standard-16-lssd","p":0.315744},{"t":"c3d-standard-180","p":3.5521200000000004},{"t":"c3d-standard-180-lssd","p":3.5521200000000004},{"t":"c3d-standard-30","p":0.59202},{"t":"c3d-standard-30-lssd","p":0.59202},{"t":"c3d-standard-360","p":7.104240000000001},{"t":"c3d-standard-360-lssd","p":7.104240000000001},{"t":"c3d-standard-4","p":0.078936},{"t":"c3d-standard-60","p":1.18404},{"t":"c3d-standard-60-lssd","p":1.18404},{"t":"c3d-standard-8","p":0.157872},{"t":"c3d-standard-8-lssd","p":0.157872},{"t":"c3d-standard-90","p":1.7760600000000002},{"t":"c3d-standard-90-lssd","p":1.7760600000000002},{"t":"c4-highcpu-144","p":3.536352},{"t":"c4-highcpu-16","p":0.392928},{"t":"c4-highcpu-192","p":4.715136},{"t":"c4-highcpu-2","p":0.049116},{"t":"c4-highcpu-24","p":0.589392},{"t":"c4-highcpu-288","p":7.072704},{"t":"c4-highcpu-288-metal","p":4.163904},{"t":"c4-highcpu-32","p":0.785856},{"t":"c4-highcpu-4","p":0.098232},{"t":"c4-highcpu-48","p":1.178784},{"t":"c4-highcpu-8","p":0.196464},{"t":"c4-highcpu-96","p":2.357568},{"t":"c4-highmem-144","p":5.419224},{"t":"c4-highmem-144-lssd","p":5.419224},{"t":"c4-highmem-16","p":0.602136},{"t":"c4-highmem-16-lssd","p":0.602136},{"t":"c4-highmem-192","p":7.225632},{"t":"c4-highmem-192-lssd","p":7.225632},{"t":"c4-highmem-2","p":0.07413},{"t":"c4-highmem-24","p":0.903204},{"t":"c4-highmem-24-lssd","p":0.903204},{"t":"c4-highmem-288","p":10.838448},{"t":"c4-highmem-288-lssd","p":10.838448},{"t":"c4-highmem-288-lssd-metal","p":10.838448},{"t":"c4-highmem-288-metal","p":10.838448},{"t":"c4-highmem-32","p":1.204272},{"t":"c4-highmem-32-lssd","p":1.204272},{"t":"c4-highmem-4","p":0.150534},{"t":"c4-highmem-4-lssd","p":0.150534},{"t":"c4-highmem-48","p":1.806408},{"t":"c4-highmem-48-lssd","p":1.806408},{"t":"c4-highmem-8","p":0.301068},{"t":"c4-highmem-8-lssd","p":0.301068},{"t":"c4-highmem-96","p":3.612816},{"t":"c4-highmem-96-lssd","p":3.612816},{"t":"c4-standard-144","p":4.1094},{"t":"c4-standard-144-lssd","p":4.1094},{"t":"c4-standard-16","p":0.4566},{"t":"c4-standard-16-lssd","p":0.4566},{"t":"c4-standard-192","p":5.4792000000000005},{"t":"c4-standard-192-lssd","p":5.4792000000000005},{"t":"c4-standard-2","p":0.055938},{"t":"c4-standard-24","p":0.6849000000000001},{"t":"c4-standard-24-lssd","p":0.6849000000000001},{"t":"c4-standard-288","p":8.2188},{"t":"c4-standard-288-lssd","p":8.2188},{"t":"c4-standard-288-lssd-metal","p":8.2188},{"t":"c4-standard-288-metal","p":8.2188},{"t":"c4-standard-32","p":0.9132},{"t":"c4-standard-32-lssd","p":0.9132},{"t":"c4-standard-4","p":0.11415},{"t":"c4-standard-4-lssd","p":0.11415},{"t":"c4-standard-48","p":1.3698000000000001},{"t":"c4-standard-48-lssd","p":1.3698000000000001},{"t":"c4-standard-8","p":0.2283},{"t":"c4-standard-8-lssd","p":0.2283},{"t":"c4-standard-96","p":2.7396000000000003},{"t":"c4-standard-96-lssd","p":2.7396000000000003},{"t":"c4a-highcpu-1","p":0.020844},{"t":"c4a-highcpu-16","p":0.333504},{"t":"c4a-highcpu-2","p":0.041688},{"t":"c4a-highcpu-32","p":0.667008},{"t":"c4a-highcpu-4","p":0.083376},{"t":"c4a-highcpu-48","p":1.000512},{"t":"c4a-highcpu-64","p":1.334016},{"t":"c4a-highcpu-72","p":1.500768},{"t":"c4a-highcpu-8","p":0.166752},{"t":"c4a-highmem-1","p":0.032436000000000006},{"t":"c4a-highmem-16","p":0.5189760000000001},{"t":"c4a-highmem-16-lssd","p":0.5189760000000001},{"t":"c4a-highmem-2","p":0.06487200000000001},{"t":"c4a-highmem-32","p":1.0379520000000002},{"t":"c4a-highmem-32-lssd","p":1.0379520000000002},{"t":"c4a-highmem-4","p":0.12974400000000003},{"t":"c4a-highmem-4-lssd","p":0.12974400000000003},{"t":"c4a-highmem-48","p":1.556928},{"t":"c4a-highmem-48-lssd","p":1.556928},{"t":"c4a-highmem-64","p":2.0759040000000004},{"t":"c4a-highmem-64-lssd","p":2.0759040000000004},{"t":"c4a-highmem-72","p":2.335392},{"t":"c4a-highmem-72-lssd","p":2.335392},{"t":"c4a-highmem-8","p":0.25948800000000005},{"t":"c4a-highmem-8-lssd","p":0.25948800000000005},{"t":"c4a-highmem-96-metal","p":3.113856},{"t":"c4a-standard-1","p":0.024708},{"t":"c4a-standard-16","p":0.395328},{"t":"c4a-standard-16-lssd","p":0.395328},{"t":"c4a-standard-2","p":0.049416},{"t":"c4a-standard-32","p":0.790656},{"t":"c4a-standard-32-lssd","p":0.790656},{"t":"c4a-standard-4","p":0.098832},{"t":"c4a-standard-4-lssd","p":0.098832},{"t":"c4a-standard-48","p":1.1859840000000001},{"t":"c4a-standard-48-lssd","p":1.1859840000000001},{"t":"c4a-standard-64","p":1.581312},{"t":"c4a-standard-64-lssd","p":1.581312},{"t":"c4a-standard-72","p":1.7789760000000001},{"t":"c4a-standard-72-lssd","p":1.7789760000000001},{"t":"c4a-standard-8","p":0.197664},{"t":"c4a-standard-8-lssd","p":0.197664},{"t":"c4d-highcpu-16","p":0.24201},{"t":"c4d-highcpu-192","p":2.90412},{"t":"c4d-highcpu-2","p":0.029241},{"t":"c4d-highcpu-32","p":0.48402},{"t":"c4d-highcpu-384","p":5.80824},{"t":"c4d-highcpu-384-metal","p":5.872896},{"t":"c4d-highcpu-4","p":0.059829},{"t":"c4d-highcpu-48","p":0.72603},{"t":"c4d-highcpu-64","p":0.96804},{"t":"c4d-highcpu-8","p":0.121005},{"t":"c4d-highcpu-96","p":1.45206},{"t":"c4d-highmem-16","p":0.37132200000000004},{"t":"c4d-highmem-16-lssd","p":0.37132200000000004},{"t":"c4d-highmem-192","p":4.455864},{"t":"c4d-highmem-192-lssd","p":4.455864},{"t":"c4d-highmem-2","p":0.045405},{"t":"c4d-highmem-32","p":0.7426440000000001},{"t":"c4d-highmem-32-lssd","p":0.7426440000000001},{"t":"c4d-highmem-384","p":8.911728},{"t":"c4d-highmem-384-lssd","p":8.911728},{"t":"c4d-highmem-384-metal","p":8.976384},{"t":"c4d-highmem-4","p":0.092157},{"t":"c4d-highmem-48","p":1.113966},{"t":"c4d-highmem-48-lssd","p":1.113966},{"t":"c4d-highmem-64","p":1.4852880000000002},{"t":"c4d-highmem-64-lssd","p":1.4852880000000002},{"t":"c4d-highmem-8","p":0.18566100000000002},{"t":"c4d-highmem-8-lssd","p":0.18566100000000002},{"t":"c4d-highmem-96","p":2.227932},{"t":"c4d-highmem-96-lssd","p":2.227932},{"t":"c4d-standard-16","p":0.285114},{"t":"c4d-standard-16-lssd","p":0.285114},{"t":"c4d-standard-192","p":3.421368},{"t":"c4d-standard-192-lssd","p":3.421368},{"t":"c4d-standard-2","p":0.034629},{"t":"c4d-standard-32","p":0.570228},{"t":"c4d-standard-32-lssd","p":0.570228},{"t":"c4d-standard-384","p":6.842736},{"t":"c4d-standard-384-lssd","p":6.842736},{"t":"c4d-standard-384-metal","p":6.907392},{"t":"c4d-standard-4","p":0.070605},{"t":"c4d-standard-48","p":0.855342},{"t":"c4d-standard-48-lssd","p":0.855342},{"t":"c4d-standard-64","p":1.140456},{"t":"c4d-standard-64-lssd","p":1.140456},{"t":"c4d-standard-8","p":0.142557},{"t":"c4d-standard-8-lssd","p":0.142557},{"t":"c4d-standard-96","p":1.710684},{"t":"c4d-standard-96-lssd","p":1.710684},{"t":"e2-highcpu-16","p":0.23278400000000002},{"t":"e2-highcpu-2","p":0.029098000000000002},{"t":"e2-highcpu-32","p":0.46556800000000004},{"t":"e2-highcpu-4","p":0.058196000000000005},{"t":"e2-highcpu-8","p":0.11639200000000001},{"t":"e2-highmem-16","p":0.425312},{"t":"e2-highmem-2","p":0.053164},{"t":"e2-highmem-4","p":0.106328},{"t":"e2-highmem-8","p":0.212656},{"t":"e2-medium","p":0.032536},{"t":"e2-micro","p":0.027379},{"t":"e2-small","p":0.029098000000000002},{"t":"e2-standard-16","p":0.315296},{"t":"e2-standard-2","p":0.039412},{"t":"e2-standard-32","p":0.630592},{"t":"e2-standard-4","p":0.078824},{"t":"e2-standard-8","p":0.157648},{"t":"f1-micro","p":0.001175},{"t":"g1-small","p":0.002601},{"t":"g2-standard-12","p":0.439588},{"t":"g2-standard-16","p":0.504084},{"t":"g2-standard-24","p":0.879176},{"t":"g2-standard-32","p":0.762068},{"t":"g2-standard-4","p":0.310596},{"t":"g2-standard-48","p":1.758352},{"t":"g2-standard-8","p":0.375092},{"t":"g2-standard-96","p":3.516704},{"t":"m1-megamem-96","p":1.95424},{"t":"m1-ultramem-160","p":4.639},{"t":"m1-ultramem-40","p":1.15975},{"t":"m1-ultramem-80","p":2.3195},{"t":"m3-megamem-128","p":2.4753920000000003},{"t":"m3-megamem-64","p":1.2376960000000001},{"t":"m3-ultramem-128","p":4.185344000000001},{"t":"m3-ultramem-32","p":1.0463360000000002},{"t":"m3-ultramem-64","p":2.0926720000000003},{"t":"m4-hypermem-16","p":0.5304},{"t":"m4-hypermem-32","p":1.0608},{"t":"m4-hypermem-64","p":2.1216},{"t":"m4-megamem-112","p":3.2912},{"t":"m4-megamem-224","p":6.5824},{"t":"m4-megamem-28","p":0.8228},{"t":"m4-megamem-56","p":1.6456},{"t":"m4-ultramem-112","p":5.8208},{"t":"m4-ultramem-224","p":11.6416},{"t":"m4-ultramem-56","p":2.9104},{"t":"n1-highcpu-16","p":0.14846443359375},{"t":"n1-highcpu-2","p":0.018557783203125},{"t":"n1-highcpu-32","p":0.296927783203125},{"t":"n1-highcpu-4","p":0.03711556640625},{"t":"n1-highcpu-64","p":0.59385556640625},{"t":"n1-highcpu-8","p":0.074232216796875},{"t":"n1-highcpu-96","p":0.89078443359375},{"t":"n1-highmem-16","p":0.24792000000000003},{"t":"n1-highmem-2","p":0.030990000000000004},{"t":"n1-highmem-32","p":0.49584000000000006},{"t":"n1-highmem-4","p":0.06198000000000001},{"t":"n1-highmem-64","p":0.9916800000000001},{"t":"n1-highmem-8","p":0.12396000000000001},{"t":"n1-highmem-96","p":1.48752},{"t":"n1-megamem-96","p":2.38617556640625},{"t":"n1-standard-1","p":0.012442500000000002},{"t":"n1-standard-16","p":0.19908000000000003},{"t":"n1-standard-2","p":0.024885000000000004},{"t":"n1-standard-32","p":0.39816000000000007},{"t":"n1-standard-4","p":0.04977000000000001},{"t":"n1-standard-64","p":0.7963200000000001},{"t":"n1-standard-8","p":0.09954000000000002},{"t":"n1-standard-96","p":1.19448},{"t":"n1-ultramem-160","p":5.59164},{"t":"n1-ultramem-40","p":1.39791},{"t":"n1-ultramem-80","p":2.79582},{"t":"n2-highcpu-16","p":0.134448},{"t":"n2-highcpu-2","p":0.016806},{"t":"n2-highcpu-32","p":0.268896},{"t":"n2-highcpu-4","p":0.033612},{"t":"n2-highcpu-48","p":0.40334400000000004},{"t":"n2-highcpu-64","p":0.537792},{"t":"n2-highcpu-8","p":0.067224},{"t":"n2-highcpu-80","p":0.6722400000000001},{"t":"n2-highcpu-96","p":0.8066880000000001},{"t":"n2-highmem-128","p":1.806432},{"t":"n2-highmem-16","p":0.245664},{"t":"n2-highmem-2","p":0.030708},{"t":"n2-highmem-32","p":0.491328},{"t":"n2-highmem-4","p":0.061416},{"t":"n2-highmem-48","p":0.7369920000000001},{"t":"n2-highmem-64","p":0.982656},{"t":"n2-highmem-8","p":0.122832},{"t":"n2-highmem-80","p":1.22832},{"t":"n2-highmem-96","p":1.4739840000000002},{"t":"n2-standard-128","p":1.456896},{"t":"n2-standard-16","p":0.182112},{"t":"n2-standard-2","p":0.022764},{"t":"n2-standard-32","p":0.364224},{"t":"n2-standard-4","p":0.045528},{"t":"n2-standard-48","p":0.546336},{"t":"n2-standard-64","p":0.728448},{"t":"n2-standard-8","p":0.091056},{"t":"n2-standard-80","p":0.91056},{"t":"n2-standard-96","p":1.092672},{"t":"n2d-highcpu-128","p":2.18304},{"t":"n2d-highcpu-16","p":0.27288},{"t":"n2d-highcpu-2","p":0.03411},{"t":"n2d-highcpu-224","p":3.8203200000000006},{"t":"n2d-highcpu-32","p":0.54576},{"t":"n2d-highcpu-4","p":0.06822},{"t":"n2d-highcpu-48","p":0.8186400000000001},{"t":"n2d-highcpu-64","p":1.09152},{"t":"n2d-highcpu-8","p":0.13644},{"t":"n2d-highcpu-80","p":1.3644},{"t":"n2d-highcpu-96","p":1.6372800000000003},{"t":"n2d-highmem-16","p":0.49856000000000006},{"t":"n2d-highmem-2","p":0.06232000000000001},{"t":"n2d-highmem-32","p":0.9971200000000001},{"t":"n2d-highmem-4","p":0.12464000000000001},{"t":"n2d-highmem-48","p":1.4956800000000001},{"t":"n2d-highmem-64","p":1.9942400000000002},{"t":"n2d-highmem-8","p":0.24928000000000003},{"t":"n2d-highmem-80","p":2.4928},{"t":"n2d-highmem-96","p":2.9913600000000002},{"t":"n2d-standard-128","p":2.9568000000000003},{"t":"n2d-standard-16","p":0.36960000000000004},{"t":"n2d-standard-2","p":0.046200000000000005},{"t":"n2d-standard-224","p":5.1744},{"t":"n2d-standard-32","p":0.7392000000000001},{"t":"n2d-standard-4","p":0.09240000000000001},{"t":"n2d-standard-48","p":1.1088000000000002},{"t":"n2d-standard-64","p":1.4784000000000002},{"t":"n2d-standard-8","p":0.18480000000000002},{"t":"n2d-standard-80","p":1.848},{"t":"n2d-standard-96","p":2.2176000000000005},{"t":"n4-highcpu-16","p":0.25856},{"t":"n4-highcpu-2","p":0.03232},{"t":"n4-highcpu-32","p":0.51712},{"t":"n4-highcpu-4","p":0.06464},{"t":"n4-highcpu-48","p":0.77568},{"t":"n4-highcpu-64","p":1.03424},{"t":"n4-highcpu-8","p":0.12928},{"t":"n4-highcpu-80","p":1.2928000000000002},{"t":"n4-highmem-16","p":0.40208},{"t":"n4-highmem-2","p":0.05026},{"t":"n4-highmem-32","p":0.80416},{"t":"n4-highmem-4","p":0.10052},{"t":"n4-highmem-48","p":1.2062400000000002},{"t":"n4-highmem-64","p":1.60832},{"t":"n4-highmem-8","p":0.20104},{"t":"n4-highmem-80","p":2.0104},{"t":"n4-standard-16","p":0.3064},{"t":"n4-standard-2","p":0.0383},{"t":"n4-standard-32","p":0.6128},{"t":"n4-standard-4","p":0.0766},{"t":"n4-standard-48","p":0.9192},{"t":"n4-standard-64","p":1.2256},{"t":"n4-standard-8","p":0.1532},{"t":"n4-standard-80","p":1.532},{"t":"n4a-highcpu-1","p":0.014288000000000002},{"t":"n4a-highcpu-16","p":0.22860800000000003},{"t":"n4a-highcpu-2","p":0.028576000000000004},{"t":"n4a-highcpu-32","p":0.45721600000000007},{"t":"n4a-highcpu-4","p":0.05715200000000001},{"t":"n4a-highcpu-48","p":0.6858240000000001},{"t":"n4a-highcpu-64","p":0.9144320000000001},{"t":"n4a-highcpu-8","p":0.11430400000000002},{"t":"n4a-highmem-1","p":0.022232000000000002},{"t":"n4a-highmem-16","p":0.35571200000000003},{"t":"n4a-highmem-2","p":0.044464000000000004},{"t":"n4a-highmem-32","p":0.7114240000000001},{"t":"n4a-highmem-4","p":0.08892800000000001},{"t":"n4a-highmem-48","p":1.067136},{"t":"n4a-highmem-64","p":1.4228480000000001},{"t":"n4a-highmem-8","p":0.17785600000000001},{"t":"n4a-standard-1","p":0.016936},{"t":"n4a-standard-16","p":0.270976},{"t":"n4a-standard-2","p":0.033872},{"t":"n4a-standard-32","p":0.541952},{"t":"n4a-standard-4","p":0.067744},{"t":"n4a-standard-48","p":0.8129280000000001},{"t":"n4a-standard-64","p":1.083904},{"t":"n4a-standard-8","p":0.135488},{"t":"n4d-highcpu-16","p":0.26412800000000003},{"t":"n4d-highcpu-2","p":0.033016000000000004},{"t":"n4d-highcpu-32","p":0.5282560000000001},{"t":"n4d-highcpu-4","p":0.06603200000000001},{"t":"n4d-highcpu-48","p":0.792384},{"t":"n4d-highcpu-64","p":1.0565120000000001},{"t":"n4d-highcpu-8","p":0.13206400000000001},{"t":"n4d-highcpu-80","p":1.32064},{"t":"n4d-highcpu-96","p":1.584768},{"t":"n4d-highmem-16","p":0.41091200000000005},{"t":"n4d-highmem-2","p":0.05136400000000001},{"t":"n4d-highmem-32","p":0.8218240000000001},{"t":"n4d-highmem-4","p":0.10272800000000001},{"t":"n4d-highmem-48","p":1.232736},{"t":"n4d-highmem-64","p":1.6436480000000002},{"t":"n4d-highmem-8","p":0.20545600000000003},{"t":"n4d-highmem-80","p":2.0545600000000004},{"t":"n4d-highmem-96","p":2.465472},{"t":"n4d-standard-16","p":0.313056},{"t":"n4d-standard-2","p":0.039132},{"t":"n4d-standard-32","p":0.626112},{"t":"n4d-standard-4","p":0.078264},{"t":"n4d-standard-48","p":0.939168},{"t":"n4d-standard-64","p":1.252224},{"t":"n4d-standard-8","p":0.156528},{"t":"n4d-standard-80","p":1.56528},{"t":"n4d-standard-96","p":1.878336},{"t":"t2d-standard-1","p":0.01507},{"t":"t2d-standard-16","p":0.24112},{"t":"t2d-standard-2","p":0.03014},{"t":"t2d-standard-32","p":0.48224},{"t":"t2d-standard-4","p":0.06028},{"t":"t2d-standard-48","p":0.72336},{"t":"t2d-standard-60","p":0.9042},{"t":"t2d-standard-8","p":0.12056},{"t":"z3-highmem-14-standardlssd","p":0.2121},{"t":"z3-highmem-16-highlssd","p":0.2424},{"t":"z3-highmem-176","p":2.6664000000000003},{"t":"z3-highmem-176-standardlssd","p":2.6664000000000003},{"t":"z3-highmem-192-highlssd-metal","p":2.9088000000000003},{"t":"z3-highmem-22-highlssd","p":0.33330000000000004},{"t":"z3-highmem-22-standardlssd","p":0.33330000000000004},{"t":"z3-highmem-32-highlssd","p":0.4848},{"t":"z3-highmem-44-highlssd","p":0.6666000000000001},{"t":"z3-highmem-44-standardlssd","p":0.6666000000000001},{"t":"z3-highmem-8-highlssd","p":0.1212},{"t":"z3-highmem-88","p":1.3332000000000002},{"t":"z3-highmem-88-highlssd","p":1.3332000000000002},{"t":"z3-highmem-88-standardlssd","p":1.3332000000000002}],"europe-west4":[{"t":"a2-highgpu-1g","p":1.692835},{"t":"a2-highgpu-2g","p":3.38567},{"t":"a2-highgpu-4g","p":6.77134},{"t":"a2-highgpu-8g","p":13.54268},{"t":"a2-megagpu-16g","p":25.57624},{"t":"a2-ultragpu-1g","p":2.8068299999999997},{"t":"a2-ultragpu-2g","p":5.613659999999999},{"t":"a2-ultragpu-4g","p":11.227319999999999},{"t":"a2-ultragpu-8g","p":22.454639999999998},{"t":"a3-edgegpu-8g","p":41.627456},{"t":"a3-edgegpu-8g-nolssd","p":41.627456},{"t":"a3-highgpu-1g","p":5.203432},{"t":"a3-highgpu-2g","p":10.406864},{"t":"a3-highgpu-4g","p":20.813728},{"t":"a3-highgpu-8g","p":41.627456},{"t":"a3-megagpu-8g","p":44.776704},{"t":"a3-ultragpu-8g","p":50.507848},{"t":"a3-ultragpu-8g-nolssd","p":50.507848},{"t":"c2-standard-16","p":0.382176},{"t":"c2-standard-30","p":0.71658},{"t":"c2-standard-4","p":0.095544},{"t":"c2-standard-60","p":1.43316},{"t":"c2-standard-8","p":0.191088},{"t":"c2d-highcpu-112","p":1.8771200000000001},{"t":"c2d-highcpu-16","p":0.26816},{"t":"c2d-highcpu-2","p":0.03352},{"t":"c2d-highcpu-32","p":0.53632},{"t":"c2d-highcpu-4","p":0.06704},{"t":"c2d-highcpu-56","p":0.9385600000000001},{"t":"c2d-highcpu-8","p":0.13408},{"t":"c2d-highmem-112","p":3.06656},{"t":"c2d-highmem-16","p":0.43808},{"t":"c2d-highmem-2","p":0.05476},{"t":"c2d-highmem-32","p":0.87616},{"t":"c2d-highmem-4","p":0.10952},{"t":"c2d-highmem-56","p":1.53328},{"t":"c2d-highmem-8","p":0.21904},{"t":"c2d-standard-112","p":2.2736},{"t":"c2d-standard-16","p":0.32480000000000003},{"t":"c2d-standard-2","p":0.040600000000000004},{"t":"c2d-standard-32","p":0.6496000000000001},{"t":"c2d-standard-4","p":0.08120000000000001},{"t":"c2d-standard-56","p":1.1368},{"t":"c2d-standard-8","p":0.16240000000000002},{"t":"c3-highcpu-176","p":3.492896},{"t":"c3-highcpu-192-metal","p":4.0456959999999995},{"t":"c3-highcpu-22","p":0.436612},{"t":"c3-highcpu-4","p":0.079384},{"t":"c3-highcpu-44","p":0.873224},{"t":"c3-highcpu-8","p":0.158768},{"t":"c3-highcpu-88","p":1.746448},{"t":"c3-highmem-176","p":5.4338239999999995},{"t":"c3-highmem-192-metal","p":5.927808},{"t":"c3-highmem-22","p":0.6792279999999999},{"t":"c3-highmem-4","p":0.123496},{"t":"c3-highmem-44","p":1.3584559999999999},{"t":"c3-highmem-8","p":0.246992},{"t":"c3-highmem-88","p":2.7169119999999998},{"t":"c3-standard-176","p":4.139872},{"t":"c3-standard-176-lssd","p":4.139872},{"t":"c3-standard-192-metal","p":4.516223999999999},{"t":"c3-standard-22","p":0.517484},{"t":"c3-standard-22-lssd","p":0.517484},{"t":"c3-standard-4","p":0.094088},{"t":"c3-standard-4-lssd","p":0.094088},{"t":"c3-standard-44","p":1.034968},{"t":"c3-standard-44-lssd","p":1.034968},{"t":"c3-standard-8","p":0.188176},{"t":"c3-standard-8-lssd","p":0.188176},{"t":"c3-standard-88","p":2.069936},{"t":"c3-standard-88-lssd","p":2.069936},{"t":"c3d-highcpu-16","p":0.34688},{"t":"c3d-highcpu-180","p":3.8886600000000002},{"t":"c3d-highcpu-30","p":0.64811},{"t":"c3d-highcpu-360","p":7.7773200000000005},{"t":"c3d-highcpu-4","p":0.08672},{"t":"c3d-highcpu-60","p":1.29622},{"t":"c3d-highcpu-8","p":0.17344},{"t":"c3d-highcpu-90","p":1.9443300000000001},{"t":"c3d-highmem-16","p":0.56672},{"t":"c3d-highmem-16-lssd","p":0.3497},{"t":"c3d-highmem-180","p":6.3756},{"t":"c3d-highmem-180-lssd","p":3.9337},{"t":"c3d-highmem-30","p":1.0626},{"t":"c3d-highmem-30-lssd","p":0.6556},{"t":"c3d-highmem-360","p":12.7512},{"t":"c3d-highmem-360-lssd","p":7.8674},{"t":"c3d-highmem-4","p":0.14168},{"t":"c3d-highmem-60","p":2.1252},{"t":"c3d-highmem-60-lssd","p":1.3112},{"t":"c3d-highmem-8","p":0.28336},{"t":"c3d-highmem-8-lssd","p":0.1748},{"t":"c3d-highmem-90","p":3.1878},{"t":"c3d-highmem-90-lssd","p":1.9669},{"t":"c3d-standard-16","p":0.42016},{"t":"c3d-standard-16-lssd","p":0.42016},{"t":"c3d-standard-180","p":4.726800000000001},{"t":"c3d-standard-180-lssd","p":4.726800000000001},{"t":"c3d-standard-30","p":0.7878000000000001},{"t":"c3d-standard-30-lssd","p":0.7878000000000001},{"t":"c3d-standard-360","p":9.453600000000002},{"t":"c3d-standard-360-lssd","p":9.453600000000002},{"t":"c3d-standard-4","p":0.10504},{"t":"c3d-standard-60","p":1.5756000000000001},{"t":"c3d-standard-60-lssd","p":1.5756000000000001},{"t":"c3d-standard-8","p":0.21008},{"t":"c3d-standard-8-lssd","p":0.21008},{"t":"c3d-standard-90","p":2.3634000000000004},{"t":"c3d-standard-90-lssd","p":2.3634000000000004},{"t":"c4-highcpu-144","p":2.320416},{"t":"c4-highcpu-16","p":0.257824},{"t":"c4-highcpu-192","p":3.093888},{"t":"c4-highcpu-2","p":0.032228},{"t":"c4-highcpu-24","p":0.386736},{"t":"c4-highcpu-288","p":4.640832},{"t":"c4-highcpu-288-metal","p":5.143824},{"t":"c4-highcpu-32","p":0.515648},{"t":"c4-highcpu-4","p":0.064456},{"t":"c4-highcpu-48","p":0.773472},{"t":"c4-highcpu-8","p":0.128912},{"t":"c4-highcpu-96","p":1.546944},{"t":"c4-highmem-144","p":3.555792},{"t":"c4-highmem-144-lssd","p":3.555792},{"t":"c4-highmem-16","p":0.395088},{"t":"c4-highmem-16-lssd","p":0.395088},{"t":"c4-highmem-192","p":4.741056},{"t":"c4-highmem-192-lssd","p":4.741056},{"t":"c4-highmem-2","p":0.04864},{"t":"c4-highmem-24","p":0.592632},{"t":"c4-highmem-24-lssd","p":0.592632},{"t":"c4-highmem-288","p":7.111584},{"t":"c4-highmem-288-lssd","p":7.111584},{"t":"c4-highmem-288-lssd-metal","p":7.111584},{"t":"c4-highmem-288-metal","p":7.111584},{"t":"c4-highmem-32","p":0.790176},{"t":"c4-highmem-32-lssd","p":0.790176},{"t":"c4-highmem-4","p":0.098772},{"t":"c4-highmem-4-lssd","p":0.098772},{"t":"c4-highmem-48","p":1.185264},{"t":"c4-highmem-48-lssd","p":1.185264},{"t":"c4-highmem-8","p":0.197544},{"t":"c4-highmem-8-lssd","p":0.197544},{"t":"c4-highmem-96","p":2.370528},{"t":"c4-highmem-96-lssd","p":2.370528},{"t":"c4-standard-144","p":2.6964},{"t":"c4-standard-144-lssd","p":2.6964},{"t":"c4-standard-16","p":0.2996},{"t":"c4-standard-16-lssd","p":0.2996},{"t":"c4-standard-192","p":3.5952},{"t":"c4-standard-192-lssd","p":3.5952},{"t":"c4-standard-2","p":0.036704},{"t":"c4-standard-24","p":0.4494},{"t":"c4-standard-24-lssd","p":0.4494},{"t":"c4-standard-288","p":5.3928},{"t":"c4-standard-288-lssd","p":5.3928},{"t":"c4-standard-288-lssd-metal","p":5.3928},{"t":"c4-standard-288-metal","p":5.3928},{"t":"c4-standard-32","p":0.5992},{"t":"c4-standard-32-lssd","p":0.5992},{"t":"c4-standard-4","p":0.0749},{"t":"c4-standard-4-lssd","p":0.0749},{"t":"c4-standard-48","p":0.8988},{"t":"c4-standard-48-lssd","p":0.8988},{"t":"c4-standard-8","p":0.1498},{"t":"c4-standard-8-lssd","p":0.1498},{"t":"c4-standard-96","p":1.7976},{"t":"c4-standard-96-lssd","p":1.7976},{"t":"c4a-highcpu-1","p":0.0066040000000000005},{"t":"c4a-highcpu-16","p":0.10566400000000001},{"t":"c4a-highcpu-2","p":0.013208000000000001},{"t":"c4a-highcpu-32","p":0.21132800000000002},{"t":"c4a-highcpu-4","p":0.026416000000000002},{"t":"c4a-highcpu-48","p":0.31699200000000005},{"t":"c4a-highcpu-64","p":0.42265600000000003},{"t":"c4a-highcpu-72","p":0.475488},{"t":"c4a-highcpu-8","p":0.052832000000000004},{"t":"c4a-highmem-1","p":0.010276},{"t":"c4a-highmem-16","p":0.164416},{"t":"c4a-highmem-16-lssd","p":0.164416},{"t":"c4a-highmem-2","p":0.020552},{"t":"c4a-highmem-32","p":0.328832},{"t":"c4a-highmem-32-lssd","p":0.328832},{"t":"c4a-highmem-4","p":0.041104},{"t":"c4a-highmem-4-lssd","p":0.041104},{"t":"c4a-highmem-48","p":0.493248},{"t":"c4a-highmem-48-lssd","p":0.493248},{"t":"c4a-highmem-64","p":0.657664},{"t":"c4a-highmem-64-lssd","p":0.657664},{"t":"c4a-highmem-72","p":0.7398720000000001},{"t":"c4a-highmem-72-lssd","p":0.7398720000000001},{"t":"c4a-highmem-8","p":0.082208},{"t":"c4a-highmem-8-lssd","p":0.082208},{"t":"c4a-highmem-96-metal","p":0.986496},{"t":"c4a-standard-1","p":0.007828},{"t":"c4a-standard-16","p":0.125248},{"t":"c4a-standard-16-lssd","p":0.125248},{"t":"c4a-standard-2","p":0.015656},{"t":"c4a-standard-32","p":0.250496},{"t":"c4a-standard-32-lssd","p":0.250496},{"t":"c4a-standard-4","p":0.031312},{"t":"c4a-standard-4-lssd","p":0.031312},{"t":"c4a-standard-48","p":0.375744},{"t":"c4a-standard-48-lssd","p":0.375744},{"t":"c4a-standard-64","p":0.500992},{"t":"c4a-standard-64-lssd","p":0.500992},{"t":"c4a-standard-72","p":0.563616},{"t":"c4a-standard-72-lssd","p":0.563616},{"t":"c4a-standard-8","p":0.062624},{"t":"c4a-standard-8-lssd","p":0.062624},{"t":"c4d-highcpu-16","p":0.25027000000000005},{"t":"c4d-highcpu-192","p":3.0032400000000004},{"t":"c4d-highcpu-2","p":0.030239000000000002},{"t":"c4d-highcpu-32","p":0.5005400000000001},{"t":"c4d-highcpu-384","p":6.006480000000001},{"t":"c4d-highcpu-384-metal","p":6.0733440000000005},{"t":"c4d-highcpu-4","p":0.06187100000000001},{"t":"c4d-highcpu-48","p":0.7508100000000001},{"t":"c4d-highcpu-64","p":1.0010800000000002},{"t":"c4d-highcpu-8","p":0.12513500000000002},{"t":"c4d-highcpu-96","p":1.5016200000000002},{"t":"c4d-highmem-16","p":0.38399800000000006},{"t":"c4d-highmem-16-lssd","p":0.38399800000000006},{"t":"c4d-highmem-192","p":4.607976000000001},{"t":"c4d-highmem-192-lssd","p":4.607976000000001},{"t":"c4d-highmem-2","p":0.04695500000000001},{"t":"c4d-highmem-32","p":0.7679960000000001},{"t":"c4d-highmem-32-lssd","p":0.7679960000000001},{"t":"c4d-highmem-384","p":9.215952000000001},{"t":"c4d-highmem-384-lssd","p":9.215952000000001},{"t":"c4d-highmem-384-metal","p":9.282816},{"t":"c4d-highmem-4","p":0.09530300000000001},{"t":"c4d-highmem-48","p":1.1519940000000002},{"t":"c4d-highmem-48-lssd","p":1.1519940000000002},{"t":"c4d-highmem-64","p":1.5359920000000002},{"t":"c4d-highmem-64-lssd","p":1.5359920000000002},{"t":"c4d-highmem-8","p":0.19199900000000003},{"t":"c4d-highmem-8-lssd","p":0.19199900000000003},{"t":"c4d-highmem-96","p":2.3039880000000004},{"t":"c4d-highmem-96-lssd","p":2.3039880000000004},{"t":"c4d-standard-16","p":0.29484600000000005},{"t":"c4d-standard-16-lssd","p":0.29484600000000005},{"t":"c4d-standard-192","p":3.5381520000000006},{"t":"c4d-standard-192-lssd","p":3.5381520000000006},{"t":"c4d-standard-2","p":0.035811},{"t":"c4d-standard-32","p":0.5896920000000001},{"t":"c4d-standard-32-lssd","p":0.5896920000000001},{"t":"c4d-standard-384","p":7.076304000000001},{"t":"c4d-standard-384-lssd","p":7.076304000000001},{"t":"c4d-standard-384-metal","p":7.143168000000001},{"t":"c4d-standard-4","p":0.07301500000000001},{"t":"c4d-standard-48","p":0.8845380000000002},{"t":"c4d-standard-48-lssd","p":0.8845380000000002},{"t":"c4d-standard-64","p":1.1793840000000002},{"t":"c4d-standard-64-lssd","p":1.1793840000000002},{"t":"c4d-standard-8","p":0.14742300000000003},{"t":"c4d-standard-8-lssd","p":0.14742300000000003},{"t":"c4d-standard-96","p":1.7690760000000003},{"t":"c4d-standard-96-lssd","p":1.7690760000000003},{"t":"e2-highcpu-16","p":0.19832},{"t":"e2-highcpu-2","p":0.02479},{"t":"e2-highcpu-32","p":0.39664},{"t":"e2-highcpu-4","p":0.04958},{"t":"e2-highcpu-8","p":0.09916},{"t":"e2-highmem-16","p":0.36240000000000006},{"t":"e2-highmem-2","p":0.04530000000000001},{"t":"e2-highmem-4","p":0.09060000000000001},{"t":"e2-highmem-8","p":0.18120000000000003},{"t":"e2-medium","p":0.02772},{"t":"e2-micro","p":0.023325000000000002},{"t":"e2-small","p":0.02479},{"t":"e2-standard-16","p":0.26864},{"t":"e2-standard-2","p":0.03358},{"t":"e2-standard-32","p":0.53728},{"t":"e2-standard-4","p":0.06716},{"t":"e2-standard-8","p":0.13432},{"t":"f1-micro","p":0.00079},{"t":"g1-small","p":0.004542},{"t":"g2-standard-12","p":0.55178},{"t":"g2-standard-16","p":0.63274},{"t":"g2-standard-24","p":1.10356},{"t":"g2-standard-32","p":0.95658},{"t":"g2-standard-4","p":0.38986},{"t":"g2-standard-48","p":2.20712},{"t":"g2-standard-8","p":0.47082},{"t":"g2-standard-96","p":4.41424},{"t":"h3-standard-88","p":1.48896},{"t":"h4d-highmem-192","p":3.592944},{"t":"h4d-highmem-192-lssd","p":3.592944},{"t":"h4d-standard-192","p":3.19128},{"t":"m1-megamem-96","p":1.108761392578125},{"t":"m1-ultramem-160","p":2.6203640000000004},{"t":"m1-ultramem-40","p":0.6550910000000001},{"t":"m1-ultramem-80","p":1.3101820000000002},{"t":"m3-megamem-128","p":1.375584},{"t":"m3-megamem-64","p":0.687792},{"t":"m3-ultramem-128","p":2.326208},{"t":"m3-ultramem-32","p":0.581552},{"t":"m3-ultramem-64","p":1.163104},{"t":"m4-hypermem-16","p":0.7722},{"t":"m4-hypermem-32","p":1.5444},{"t":"m4-hypermem-64","p":3.0888},{"t":"m4-megamem-112","p":4.7916},{"t":"m4-megamem-224","p":9.5832},{"t":"m4-megamem-28","p":1.1979},{"t":"m4-megamem-56","p":2.3958},{"t":"m4-ultramem-112","p":8.4744},{"t":"m4-ultramem-224","p":16.9488},{"t":"m4-ultramem-56","p":4.2372},{"t":"n1-highcpu-16","p":0.3297225625},{"t":"n1-highcpu-2","p":0.041214718750000004},{"t":"n1-highcpu-32","p":0.65944271875},{"t":"n1-highcpu-4","p":0.08242943750000001},{"t":"n1-highcpu-64","p":1.3188854375},{"t":"n1-highcpu-8","p":0.16486128125},{"t":"n1-highcpu-96","p":1.9783305624999998},{"t":"n1-highmem-16","p":0.550496},{"t":"n1-highmem-2","p":0.068812},{"t":"n1-highmem-32","p":1.100992},{"t":"n1-highmem-4","p":0.137624},{"t":"n1-highmem-64","p":2.201984},{"t":"n1-highmem-8","p":0.275248},{"t":"n1-highmem-96","p":3.302976},{"t":"n1-megamem-96","p":5.2978294375},{"t":"n1-standard-1","p":0.027630000000000002},{"t":"n1-standard-16","p":0.44208000000000003},{"t":"n1-standard-2","p":0.055260000000000004},{"t":"n1-standard-32","p":0.8841600000000001},{"t":"n1-standard-4","p":0.11052000000000001},{"t":"n1-standard-64","p":1.7683200000000001},{"t":"n1-standard-8","p":0.22104000000000001},{"t":"n1-standard-96","p":2.6524799999999997},{"t":"n1-ultramem-160","p":12.414016},{"t":"n1-ultramem-40","p":3.103504},{"t":"n1-ultramem-80","p":6.207008},{"t":"n2-highcpu-16","p":0.24168},{"t":"n2-highcpu-2","p":0.03021},{"t":"n2-highcpu-32","p":0.48336},{"t":"n2-highcpu-4","p":0.06042},{"t":"n2-highcpu-48","p":0.72504},{"t":"n2-highcpu-64","p":0.96672},{"t":"n2-highcpu-8","p":0.12084},{"t":"n2-highcpu-80","p":1.2084000000000001},{"t":"n2-highcpu-96","p":1.45008},{"t":"n2-highmem-128","p":3.2472000000000003},{"t":"n2-highmem-16","p":0.4416},{"t":"n2-highmem-2","p":0.0552},{"t":"n2-highmem-32","p":0.8832},{"t":"n2-highmem-4","p":0.1104},{"t":"n2-highmem-48","p":1.3248000000000002},{"t":"n2-highmem-64","p":1.7664},{"t":"n2-highmem-8","p":0.2208},{"t":"n2-highmem-80","p":2.208},{"t":"n2-highmem-96","p":2.6496000000000004},{"t":"n2-standard-128","p":2.61888},{"t":"n2-standard-16","p":0.32736},{"t":"n2-standard-2","p":0.04092},{"t":"n2-standard-32","p":0.65472},{"t":"n2-standard-4","p":0.08184},{"t":"n2-standard-48","p":0.9820800000000001},{"t":"n2-standard-64","p":1.30944},{"t":"n2-standard-8","p":0.16368},{"t":"n2-standard-80","p":1.6368},{"t":"n2-standard-96","p":1.9641600000000001},{"t":"n2d-highcpu-128","p":1.3991680000000002},{"t":"n2d-highcpu-16","p":0.17489600000000002},{"t":"n2d-highcpu-2","p":0.021862000000000003},{"t":"n2d-highcpu-224","p":2.4485440000000005},{"t":"n2d-highcpu-32","p":0.34979200000000005},{"t":"n2d-highcpu-4","p":0.043724000000000006},{"t":"n2d-highcpu-48","p":0.524688},{"t":"n2d-highcpu-64","p":0.6995840000000001},{"t":"n2d-highcpu-8","p":0.08744800000000001},{"t":"n2d-highcpu-80","p":0.8744800000000001},{"t":"n2d-highcpu-96","p":1.049376},{"t":"n2d-highmem-16","p":0.319488},{"t":"n2d-highmem-2","p":0.039936},{"t":"n2d-highmem-32","p":0.638976},{"t":"n2d-highmem-4","p":0.079872},{"t":"n2d-highmem-48","p":0.958464},{"t":"n2d-highmem-64","p":1.277952},{"t":"n2d-highmem-8","p":0.159744},{"t":"n2d-highmem-80","p":1.5974400000000002},{"t":"n2d-highmem-96","p":1.916928},{"t":"n2d-standard-128","p":1.8949120000000002},{"t":"n2d-standard-16","p":0.23686400000000002},{"t":"n2d-standard-2","p":0.029608000000000002},{"t":"n2d-standard-224","p":3.3160960000000004},{"t":"n2d-standard-32","p":0.47372800000000004},{"t":"n2d-standard-4","p":0.059216000000000005},{"t":"n2d-standard-48","p":0.710592},{"t":"n2d-standard-64","p":0.9474560000000001},{"t":"n2d-standard-8","p":0.11843200000000001},{"t":"n2d-standard-80","p":1.18432},{"t":"n2d-standard-96","p":1.421184},{"t":"n4-highcpu-16","p":0.15177600000000002},{"t":"n4-highcpu-2","p":0.018972000000000003},{"t":"n4-highcpu-32","p":0.30355200000000004},{"t":"n4-highcpu-4","p":0.037944000000000006},{"t":"n4-highcpu-48","p":0.45532800000000007},{"t":"n4-highcpu-64","p":0.6071040000000001},{"t":"n4-highcpu-8","p":0.07588800000000001},{"t":"n4-highcpu-80","p":0.7588800000000001},{"t":"n4-highmem-16","p":0.23606400000000002},{"t":"n4-highmem-2","p":0.029508000000000003},{"t":"n4-highmem-32","p":0.47212800000000005},{"t":"n4-highmem-4","p":0.059016000000000006},{"t":"n4-highmem-48","p":0.708192},{"t":"n4-highmem-64","p":0.9442560000000001},{"t":"n4-highmem-8","p":0.11803200000000001},{"t":"n4-highmem-80","p":1.18032},{"t":"n4-standard-16","p":0.17987200000000003},{"t":"n4-standard-2","p":0.022484000000000004},{"t":"n4-standard-32","p":0.35974400000000006},{"t":"n4-standard-4","p":0.04496800000000001},{"t":"n4-standard-48","p":0.5396160000000001},{"t":"n4-standard-64","p":0.7194880000000001},{"t":"n4-standard-8","p":0.08993600000000002},{"t":"n4-standard-80","p":0.8993600000000002},{"t":"n4a-highcpu-1","p":0.014324000000000002},{"t":"n4a-highcpu-16","p":0.22918400000000003},{"t":"n4a-highcpu-2","p":0.028648000000000003},{"t":"n4a-highcpu-32","p":0.45836800000000005},{"t":"n4a-highcpu-4","p":0.05729600000000001},{"t":"n4a-highcpu-48","p":0.6875520000000002},{"t":"n4a-highcpu-64","p":0.9167360000000001},{"t":"n4a-highcpu-8","p":0.11459200000000001},{"t":"n4a-highmem-1","p":0.022286},{"t":"n4a-highmem-16","p":0.356576},{"t":"n4a-highmem-2","p":0.044572},{"t":"n4a-highmem-32","p":0.713152},{"t":"n4a-highmem-4","p":0.089144},{"t":"n4a-highmem-48","p":1.069728},{"t":"n4a-highmem-64","p":1.426304},{"t":"n4a-highmem-8","p":0.178288},{"t":"n4a-standard-1","p":0.016978},{"t":"n4a-standard-16","p":0.271648},{"t":"n4a-standard-2","p":0.033956},{"t":"n4a-standard-32","p":0.543296},{"t":"n4a-standard-4","p":0.067912},{"t":"n4a-standard-48","p":0.8149440000000001},{"t":"n4a-standard-64","p":1.086592},{"t":"n4a-standard-8","p":0.135824},{"t":"n4d-highcpu-16","p":0.238688},{"t":"n4d-highcpu-2","p":0.029836},{"t":"n4d-highcpu-32","p":0.477376},{"t":"n4d-highcpu-4","p":0.059672},{"t":"n4d-highcpu-48","p":0.716064},{"t":"n4d-highcpu-64","p":0.954752},{"t":"n4d-highcpu-8","p":0.119344},{"t":"n4d-highcpu-80","p":1.19344},{"t":"n4d-highcpu-96","p":1.432128},{"t":"n4d-highmem-16","p":0.371552},{"t":"n4d-highmem-2","p":0.046444},{"t":"n4d-highmem-32","p":0.743104},{"t":"n4d-highmem-4","p":0.092888},{"t":"n4d-highmem-48","p":1.114656},{"t":"n4d-highmem-64","p":1.486208},{"t":"n4d-highmem-8","p":0.185776},{"t":"n4d-highmem-80","p":1.85776},{"t":"n4d-highmem-96","p":2.229312},{"t":"n4d-standard-16","p":0.282976},{"t":"n4d-standard-2","p":0.035372},{"t":"n4d-standard-32","p":0.565952},{"t":"n4d-standard-4","p":0.070744},{"t":"n4d-standard-48","p":0.8489280000000001},{"t":"n4d-standard-64","p":1.131904},{"t":"n4d-standard-8","p":0.141488},{"t":"n4d-standard-80","p":1.4148800000000001},{"t":"n4d-standard-96","p":1.6978560000000003},{"t":"t2a-standard-1","p":0.021952},{"t":"t2a-standard-16","p":0.351232},{"t":"t2a-standard-2","p":0.043904},{"t":"t2a-standard-32","p":0.702464},{"t":"t2a-standard-4","p":0.087808},{"t":"t2a-standard-48","p":1.053696},{"t":"t2a-standard-8","p":0.175616},{"t":"t2d-standard-1","p":0.015364000000000001},{"t":"t2d-standard-16","p":0.24582400000000001},{"t":"t2d-standard-2","p":0.030728000000000002},{"t":"t2d-standard-32","p":0.49164800000000003},{"t":"t2d-standard-4","p":0.061456000000000004},{"t":"t2d-standard-48","p":0.737472},{"t":"t2d-standard-60","p":0.92184},{"t":"t2d-standard-8","p":0.12291200000000001},{"t":"z3-highmem-14-standardlssd","p":0.21929600000000002},{"t":"z3-highmem-16-highlssd","p":0.250624},{"t":"z3-highmem-176","p":2.756864},{"t":"z3-highmem-176-standardlssd","p":2.756864},{"t":"z3-highmem-192-highlssd-metal","p":3.0074880000000004},{"t":"z3-highmem-22-highlssd","p":0.344608},{"t":"z3-highmem-22-standardlssd","p":0.344608},{"t":"z3-highmem-32-highlssd","p":0.501248},{"t":"z3-highmem-44-highlssd","p":0.689216},{"t":"z3-highmem-44-standardlssd","p":0.689216},{"t":"z3-highmem-8-highlssd","p":0.125312},{"t":"z3-highmem-88","p":1.378432},{"t":"z3-highmem-88-highlssd","p":1.378432},{"t":"z3-highmem-88-standardlssd","p":1.378432}]}